LICENSE
README.md
setup.cfg
setup.py
src/zakhar_pycore/__init__.py
src/zakhar_pycore.egg-info/PKG-INFO
src/zakhar_pycore.egg-info/SOURCES.txt
src/zakhar_pycore.egg-info/dependency_links.txt
src/zakhar_pycore.egg-info/not-zip-safe
src/zakhar_pycore.egg-info/requires.txt
src/zakhar_pycore.egg-info/top_level.txt
src/zakhar_pycore/dev/__init__.py
src/zakhar_pycore/dev/dev_types.py
src/zakhar_pycore/dev/interfaces.py
src/zakhar_pycore/dev/face_module/__init__.py
src/zakhar_pycore/dev/face_module/cmd.py
src/zakhar_pycore/dev/face_module/reg.py
src/zakhar_pycore/dev/moving_platform/__init__.py
src/zakhar_pycore/dev/moving_platform/cmd.py
src/zakhar_pycore/dev/moving_platform/reg.py
src/zakhar_pycore/dev/sensor_platform/__init__.py
src/zakhar_pycore/dev/sensor_platform/cmd.py
src/zakhar_pycore/dev/sensor_platform/reg.py
src/zakhar_pycore/helpers/__init__.py
src/zakhar_pycore/helpers/format.py
src/zakhar_pycore/helpers/lists.py
src/zakhar_pycore/helpers/os.py
src/zakhar_pycore/i2c/__init__.py
src/zakhar_pycore/i2c/funcs.py
src/zakhar_pycore/i2c/low_level_i2c.py
src/zakhar_pycore/ros/__init__.py
src/zakhar_pycore/ros/get.py
src/zakhar_pycore/ros/services.py
src/zakhar_pycore/ros/topics.py