Metadata-Version: 2.1
Name: zakhar-pycore
Version: 1.3.0
Summary: Python package used by the Zakhar project (zakhar.agramakov.me). The package contains addresses of devices, command codes, hardware interfaces, etc.
Home-page: https://github.com/an-dr/zakhar_pycore
Author: Andrei Gramakov
Author-email: mail@agramakov.me
License: MIT
Keywords: robot,zakhar,robotics
Platform: UNKNOWN
Classifier: Programming Language :: Python :: 3 :: Only
Classifier: License :: OSI Approved :: MIT License
Classifier: Operating System :: Unix
Classifier: Framework :: Robot Framework :: Library
Provides-Extra: dev
